farasa/__init__.py
farasa/fitTemplateClass.py
farasa/segmentation.py
farasa/arabic_utils/__init__.py
farasa/arabic_utils/utilities.py
farasa/pickles/NTBdata.SeenBefore.ser
farasa/pickles/__init__.py
farasa/pickles/generalVariables
farasa/pickles/hPrefixes
farasa/pickles/hSuffixes
farasa/pickles/hmAraLexCom
farasa/pickles/hmBuck
farasa/pickles/hmListGaz
farasa/pickles/hmListMorph
farasa/pickles/hmLocations
farasa/pickles/hmPeople
farasa/pickles/hmPreviouslySeenTokenizations
farasa/pickles/hmSeenBefore
farasa/pickles/hmStop
farasa/pickles/hmTemplateCount
farasa/pickles/hmValidPrefixes
farasa/pickles/hmValidPrefixesSegmented
farasa/pickles/hmValidSuffixes
farasa/pickles/hmValidSuffixesSegmented
farasa/pickles/hmWordPossibleSplits
farasa/pickles/probCondPrefixes
farasa/pickles/probCondSuffixes
farasa/pickles/probPrefixSuffix
farasa/pickles/probPrefixes
farasa/pickles/probSuffixPrefix
farasa/pickles/probSuffixes
farasa/pickles/roots.txt
farasa/pickles/seenTemplates
farasa/pickles/template-count.txt
farasa/pickles/wordCount
PyFarasa-0.0.1.dist-info/LICENSE
PyFarasa-0.0.1.dist-info/METADATA
PyFarasa-0.0.1.dist-info/WHEEL
PyFarasa-0.0.1.dist-info/top_level.txt
PyFarasa-0.0.1.dist-info/RECORD
